{
  "name": "Tony Abdelmalak",
  "title": "People & Business Insights Analyst",
  "tagline": "Turning workforce data into executive-ready strategies with Tableau, SQL, Python, and AI.",
  "links": {
    "home": "/index.html",
    "projects": "/projects",
    "dashboards": "/projects#dashboards",
    "caseStudies": "/case-studies",
    "resume": "/resume",
    "about": "/about",
    "knowledge": "/knowledge/index"
  },
  "skills": [
    "Tableau & data storytelling",
    "SQL pipelines & QA",
    "Python forecasting/automation",
    "Explainable ML (attrition, risk)",
    "HRIS (Workday, SuccessFactors, Greenhouse)",
    "Lightweight AI copilots"
  ],
  "contact": {
    "email": "mailto:tony@abdelmalak.ai",
    "linkedin": "https://www.linkedin.com/in/tonyabdelmalak/"
  }
}
